pyBamTools/__init__.py
pyBamTools/coverage/__init__.py
pyBamTools/genotyping/__init__.py
pyBamTools/genotyping/naive.py
pyBamTools/util/__init__.py
pyBamTools/util/nuc.py
pyBamTools/util/odict.py
pyBamTools/util/sam.py
pyBamTools/util/vcf.py
pyBamTools-0.0.4.dist-info/DESCRIPTION.rst
pyBamTools-0.0.4.dist-info/METADATA
pyBamTools-0.0.4.dist-info/RECORD
pyBamTools-0.0.4.dist-info/WHEEL
pyBamTools-0.0.4.dist-info/metadata.json
pyBamTools-0.0.4.dist-info/top_level.txt
