Metadata-Version: 2.0
Name: pyBamTools
Version: 0.0.4
Summary: Tools for working on BAM data
Home-page: https://github.com/blankenberg/pyBamTools
Author: Daniel Blankenberg
Author-email: dan.blankenberg@gmail.com
License: GPLv2
Platform: UNKNOWN
Classifier: Development Status :: 4 - Beta
Classifier: License :: OSI Approved :: GNU General Public License v2 (GPLv2)
Requires-Dist: numpy
Requires-Dist: pyBamParser (==0.0.3)
